aioinflux1x/__init__.py
aioinflux1x/client.py
aioinflux1x/compat.py
aioinflux1x/iterutils.py
aioinflux1x/serialization/__init__.py
aioinflux1x/serialization/common.py
aioinflux1x/serialization/dataframe.py
aioinflux1x/serialization/mapping.py
aioinflux1x/serialization/usertype.py
aioinflux1x-1.0.0.dist-info/licenses/LICENSE
aioinflux1x-1.0.0.dist-info/METADATA
aioinflux1x-1.0.0.dist-info/WHEEL
aioinflux1x-1.0.0.dist-info/top_level.txt
aioinflux1x-1.0.0.dist-info/RECORD
