Metadata-Version: 2.4
Name: aioinflux1x
Version: 1.0.0
Requires-Python: >=3.8
License-File: LICENSE
Requires-Dist: aiohttp>=3.0
Requires-Dist: ciso8601
Dynamic: license-file
